{
    "display": {
        "title": {
            "translate": "roguecraft.advancement.name.speedrun"
        },
        "description": {
            "translate": "roguecraft.advancement.description.speedrun",
            "color": "green"
        },
        "icon": {
            "item": "minecraft:stick",
            "nbt": "{CustomModelData:24}"
        },
        "frame": "task",
        "show_toast": true,
        "announce_to_chat": true,
        "hidden": false
    },
    "criteria": {
        "granted": {
            "trigger": "minecraft:impossible"
        }
    },
    "parent": "roguecraft:roguecraft/run_complete"
}